README.md
setup.cfg
setup.py
Bottle_OpenTracing.egg-info/PKG-INFO
Bottle_OpenTracing.egg-info/SOURCES.txt
Bottle_OpenTracing.egg-info/dependency_links.txt
Bottle_OpenTracing.egg-info/not-zip-safe
Bottle_OpenTracing.egg-info/requires.txt
Bottle_OpenTracing.egg-info/top_level.txt
bottle_opentracing/__init__.py
bottle_opentracing/app.py
bottle_opentracing/instrument.py
bottle_opentracing/tracing.py
tests/__init__.py
tests/test_bottle_api.py
tests/test_bottle_tracing.py